{"weapons":[{"weaponId":0,"weaponName":"GLOCK","weaponBullet":10,"weaponDamage":1,"weaponPicture":"image/1.png","posx":48,"posy":48},{"weaponId":1,"weaponName":"MP5","weaponBullet":20,"weaponDamage":1,"weaponPicture":"image/2.png","posx":72,"posy":72},{"weaponId":2,"weaponName":"FAMAS","weaponBullet":30,"weaponDamage":1,"weaponPicture":"image/3.png","posx":96,"posy":96},{"weaponId":3,"weaponName":"AK47","weaponBullet":20,"weaponDamage":2,"weaponPicture":"image/4.png","posx":120,"posy":120},{"weaponId":4,"weaponName":"M4A1","weaponBullet":30,"weaponDamage":2,"weaponPicture":"image/5.png","posx":144,"posy":144},{"weaponId":5,"weaponName":"AWP","weaponBullet":10,"weaponDamage":3,"weaponPicture":"image/6.png","posx":168,"posy":168}]}